cookielaw/__init__.py
cookielaw/context_processors.py
cookielaw/models.py
cookielaw/views.py
cookielaw/locale/ca/LC_MESSAGES/django.mo
cookielaw/locale/ca/LC_MESSAGES/django.po
cookielaw/locale/de/LC_MESSAGES/django.mo
cookielaw/locale/de/LC_MESSAGES/django.po
cookielaw/locale/en/LC_MESSAGES/django.mo
cookielaw/locale/en/LC_MESSAGES/django.po
cookielaw/locale/es/LC_MESSAGES/django.mo
cookielaw/locale/es/LC_MESSAGES/django.po
cookielaw/locale/fi/LC_MESSAGES/django.mo
cookielaw/locale/fi/LC_MESSAGES/django.po
cookielaw/locale/fr/LC_MESSAGES/django.mo
cookielaw/locale/fr/LC_MESSAGES/django.po
cookielaw/locale/it/LC_MESSAGES/django.mo
cookielaw/locale/it/LC_MESSAGES/django.po
cookielaw/locale/nl/LC_MESSAGES/django.mo
cookielaw/locale/nl/LC_MESSAGES/django.po
cookielaw/locale/pl/LC_MESSAGES/django.mo
cookielaw/locale/pl/LC_MESSAGES/django.po
cookielaw/locale/ru/LC_MESSAGES/django.mo
cookielaw/locale/ru/LC_MESSAGES/django.po
cookielaw/static/cookielaw/css/cookielaw.css
cookielaw/static/cookielaw/img/close.png
cookielaw/static/cookielaw/js/cookielaw.js
cookielaw/templates/cookielaw/banner.html
cookielaw/templates/cookielaw/rejectable.html
cookielaw/templatetags/__init__.py
cookielaw/templatetags/cookielaw_tags.py
cookielaw/test_project/__init__.py
cookielaw/test_project/urls.py
cookielaw/test_project/wsgi.py
cookielaw/test_project/test_app/__init__.py
cookielaw/test_project/test_app/models.py
cookielaw/test_project/test_app/views.py
tests/__init__.py
tests/test_base.py
tests/test_functional.py
django_cookie_law-2.2.0.dist-info/LICENSE.rst
django_cookie_law-2.2.0.dist-info/METADATA
django_cookie_law-2.2.0.dist-info/WHEEL
django_cookie_law-2.2.0.dist-info/top_level.txt
django_cookie_law-2.2.0.dist-info/RECORD
