Metadata-Version: 2.1
Name: django-cookie-law
Version: 2.2.0
Summary: Helps your Django project comply with EU cookie law regulations
Home-page: https://github.com/TyMaszWeb/django-cookie-law
Author: Piotr Kilczuk
Author-email: piotr@tymaszweb.pl
License: BSD License
Platform: OS Independent
Classifier: Development Status :: 5 - Production/Stable
Classifier: Environment :: Web Environment
Classifier: Framework :: Django
Classifier: Intended Audience :: Developers
Classifier: License :: OSI Approved :: BSD License
Classifier: Operating System :: OS Independent
Classifier: Programming Language :: Python
Classifier: Programming Language :: JavaScript
Classifier: Topic :: Internet :: WWW/HTTP
Classifier: Topic :: Internet :: WWW/HTTP :: Session
License-File: LICENSE.rst
